README.md
main.py
setup.py
pysysinfo.egg-info/PKG-INFO
pysysinfo.egg-info/SOURCES.txt
pysysinfo.egg-info/dependency_links.txt
pysysinfo.egg-info/entry_points.txt
pysysinfo.egg-info/top_level.txt
pysysinfo.egg-info/zip-safe
src/__init__.py
src/android.py
src/linux.py
src/mac.py
src/rasberry.py
src/win.py