Metadata-Version: 2.1
Name: pysysinfo
Version: 0.0.1
Summary: UNKNOWN
Home-page: https://github.com/ganeshkbhat/py-device-info
Author: Ganesh B
Author-email: desktopcgi@gmail.com
Maintainer: Ganesh B
Maintainer-email: desktopcgi@gmail.com
License: Proprietary
Download-URL: https://pypi.org/project/pysysinfo/
Platform: any
Classifier: Programming Language :: Python :: 3
Classifier: License :: Free To Use But Restricted
Classifier: License :: Free For Educational Use
Classifier: License :: Freely Distributable
Classifier: Operating System :: OS Independent
